beves/__init__.py
beves/__main__.py
beves/errors.py
beves/metadata.py
beves/tests/__init__.py
beves/tests/tests.py
beves-0.1.dist-info/LICENSE.txt
beves-0.1.dist-info/METADATA
beves-0.1.dist-info/WHEEL
beves-0.1.dist-info/entry_points.txt
beves-0.1.dist-info/top_level.txt
beves-0.1.dist-info/RECORD
