Metadata-Version: 2.1
Name: beves
Version: 0.1
Summary: Simple wrapper to send notifications with Telegram Bot
Home-page: https://github.com/andremmorais/beves
Author: Andre Morais
Author-email: andremomorais@gmail.com
License: LGPLv3
Keywords: python telegram bot notification
Platform: UNKNOWN
Classifier: Development Status :: 3 - Alpha
Classifier: Intended Audience :: Developers
Classifier: License :: OSI Approved :: GNU Lesser General Public License v3 (LGPLv3)
Classifier: Operating System :: OS Independent
Classifier: Topic :: Software Development :: Libraries :: Python Modules
Classifier: Topic :: Communications :: Chat
Classifier: Topic :: Internet
Classifier: Programming Language :: Python
Classifier: Programming Language :: Python :: 3.4
Classifier: Programming Language :: Python :: 3.5
Classifier: Programming Language :: Python :: 3.6
Classifier: Programming Language :: Python :: 3.7
Requires-Dist: requests (==2.21.0)
